nmat/__init__.py
nmat/bc_uploader.py
nmat/cli.py
nmat/db.py
nmat/geo_utils.py
nmat/onyx_export.py
nmat/ose_downloader.py
nmat/query.py
nmat/runner.py
nmat/util.py
nmat/version.py
nmat/config/config.yaml
nmat/indata/sp2023berncowls.xlsx
nmat/output/onyx_export.csv
nmaquifertool-0.0.6.dist-info/METADATA
nmaquifertool-0.0.6.dist-info/WHEEL
nmaquifertool-0.0.6.dist-info/entry_points.txt
nmaquifertool-0.0.6.dist-info/top_level.txt
nmaquifertool-0.0.6.dist-info/RECORD
