Metadata-Version: 2.1
Name: nmaquifertool
Version: 0.0.6
Summary: Python tool for interacting with NM_Aquifer database
Author-email: Jake Ross <jake.ross@nmt.edu>
License: BSD-3-Clause
Keywords: water data,aquifer,database
Classifier: Programming Language :: Python :: 3
Requires-Python: >=3.7
Requires-Dist: pymssql
Requires-Dist: pyproj
Requires-Dist: pandas
Requires-Dist: openpyxl
Requires-Dist: pyyaml
Requires-Dist: click
